{
  "+79006398664": {
    "cookies": [
      {
        "comment": null,
        "comment_url": null,
        "discard": false,
        "domain": ".vk.com",
        "domain_initial_dot": true,
        "domain_specified": true,
        "expires": null,
        "name": "remixlang",
        "path": "/",
        "path_specified": true,
        "port": null,
        "port_specified": false,
        "rest": {},
        "rfc2109": false,
        "secure": false,
        "value": "0",
        "version": 0
      },
      {
        "comment": null,
        "comment_url": null,
        "discard": false,
        "domain": ".vk.com",
        "domain_initial_dot": true,
        "domain_specified": true,
        "expires": null,
        "name": "remixstlid",
        "path": "/",
        "path_specified": true,
        "port": null,
        "port_specified": false,
        "rest": {},
        "rfc2109": false,
        "secure": true,
        "value": "9065918742607982171_rO417KADJBExerAv0SKG17ZgWP3FgquAkIpbYKDKu4X",
        "version": 0
      },
      {
        "comment": null,
        "comment_url": null,
        "discard": false,
        "domain": ".vk.com",
        "domain_initial_dot": true,
        "domain_specified": true,
        "expires": null,
        "name": "remixua",
        "path": "/",
        "path_specified": true,
        "port": null,
        "port_specified": false,
        "rest": {},
        "rfc2109": false,
        "secure": true,
        "value": "43%7C-1%7C331%7C4075230497",
        "version": 0
      },
      {
        "comment": null,
        "comment_url": null,
        "discard": false,
        "domain": ".vk.com",
        "domain_initial_dot": true,
        "domain_specified": true,
        "expires": null,
        "name": "remixstid",
        "path": "/",
        "path_specified": true,
        "port": null,
        "port_specified": false,
        "rest": {},
        "rfc2109": false,
        "secure": true,
        "value": "732787726_ymwEWc4uIpjE4zYc5Nf4XFsjMxb65UHoM24gUo0FtFw",
        "version": 0
      },
      {
        "comment": null,
        "comment_url": null,
        "discard": false,
        "domain": ".vk.com",
        "domain_initial_dot": true,
        "domain_specified": true,
        "expires": null,
        "name": "remixnttpid",
        "path": "/",
        "path_specified": true,
        "port": null,
        "port_specified": false,
        "rest": {
          "HttpOnly": null
        },
        "rfc2109": false,
        "secure": true,
        "value": "vk1.a.DNqYwQknWdnOpmVK89nU9_bkUSfMWIT1PGfSwRBzZINrWM20TQsb4kWnLefn8mHumv0UEyqZ5NgGpjkifRkVt90__nyBWxAcIT6antyPDabBsyP4TF5l1aBQBZUs2UxDqAhybEto3zcYxuF1xEWd999pMdOeEoaFHXHIGR2PCv1XDT487KYG3BHDTnA4aAM3",
        "version": 0
      },
      {
        "comment": null,
        "comment_url": null,
        "discard": false,
        "domain": ".vk.com",
        "domain_initial_dot": true,
        "domain_specified": true,
        "expires": null,
        "name": "remixsid",
        "path": "/",
        "path_specified": true,
        "port": null,
        "port_specified": false,
        "rest": {
          "HttpOnly": null
        },
        "rfc2109": false,
        "secure": true,
        "value": "1_D6VZUJAobUmz859PGu9Aql6SmBxRRWkWKY5U-WHquxx-EOazytQfLMCcxLTsYl8w1ETcsy0HqvQgQuoP-mE5lg",
        "version": 0
      },
      {
        "comment": null,
        "comment_url": null,
        "discard": false,
        "domain": ".vk.com",
        "domain_initial_dot": true,
        "domain_specified": true,
        "expires": null,
        "name": "remixdmgr_tmp",
        "path": "/",
        "path_specified": true,
        "port": null,
        "port_specified": false,
        "rest": {
          "HttpOnly": null
        },
        "rfc2109": false,
        "secure": true,
        "value": "5be784c00b47cbc51b02bab4175b60f6158a3f5e19dd66cbcd36d6d2a888e0d0",
        "version": 0
      },
      {
        "comment": null,
        "comment_url": null,
        "discard": false,
        "domain": ".vk.com",
        "domain_initial_dot": true,
        "domain_specified": true,
        "expires": null,
        "name": "remixdmgr",
        "path": "/",
        "path_specified": true,
        "port": null,
        "port_specified": false,
        "rest": {
          "HttpOnly": null
        },
        "rfc2109": false,
        "secure": true,
        "value": "900fb887fe2a42471b23798a9a0998e2114b4c015aca940e1e72ccf37645303c",
        "version": 0
      },
      {
        "comment": null,
        "comment_url": null,
        "discard": false,
        "domain": ".login.vk.com",
        "domain_initial_dot": false,
        "domain_specified": true,
        "expires": null,
        "name": "p",
        "path": "/",
        "path_specified": true,
        "port": null,
        "port_specified": false,
        "rest": {
          "HttpOnly": null
        },
        "rfc2109": false,
        "secure": true,
        "value": "vk1.a.vY_l9i66vyTBBKzTvc2kHr9pxWVzazw6rkltVRZ-FAyD3vE9mGe_tHTkinowWp5_r-ISJU69uR5UYFY5kt2N4OSHJOgzVI6oQDtKiKAPkZyhziXbg51OiKjdlecTLpdbBhxXF6dW-3WV7r5N1xwgzdN_FS7pSereG6RISGmobAE",
        "version": 0
      },
      {
        "comment": null,
        "comment_url": null,
        "discard": false,
        "domain": "login.vk.com",
        "domain_initial_dot": false,
        "domain_specified": false,
        "expires": null,
        "name": "remixluas2",
        "path": "/",
        "path_specified": true,
        "port": null,
        "port_specified": false,
        "rest": {
          "HttpOnly": null
        },
        "rfc2109": false,
        "secure": true,
        "value": "M2M4OWQ4YzJmYjBiMDczMjRmNDJlMDBi",
        "version": 0
      },
      {
        "comment": null,
        "comment_url": null,
        "discard": false,
        "domain": "vk.com",
        "domain_initial_dot": false,
        "domain_specified": false,
        "expires": null,
        "name": "remixnsid",
        "path": "/",
        "path_specified": true,
        "port": null,
        "port_specified": false,
        "rest": {
          "HttpOnly": null
        },
        "rfc2109": false,
        "secure": true,
        "value": "vk1.a.9yH4770jyGYPhUF2f0BrwAA9srwNGT00rCHAY1cEScMre5YfPZ9TjxrylxNqjId0kbY4P0pzN1OlmdJG3y33b-gV2p7_72VAEsbDYad1bK6XEDUuhhIjef5RBNBDc_hqOe8qFQunM1piCJhw1dUSZmZv7SDS7cZWPHj6CIk6-Jf960-Kjaiq8v1xzsf_hxjG",
        "version": 0
      },
      {
        "comment": null,
        "comment_url": null,
        "discard": false,
        "domain": ".vk.ru",
        "domain_initial_dot": true,
        "domain_specified": true,
        "expires": null,
        "name": "remixlang",
        "path": "/",
        "path_specified": true,
        "port": null,
        "port_specified": false,
        "rest": {},
        "rfc2109": false,
        "secure": false,
        "value": "0",
        "version": 0
      },
      {
        "comment": null,
        "comment_url": null,
        "discard": false,
        "domain": ".vk.ru",
        "domain_initial_dot": true,
        "domain_specified": true,
        "expires": null,
        "name": "remixstlid",
        "path": "/",
        "path_specified": true,
        "port": null,
        "port_specified": false,
        "rest": {},
        "rfc2109": false,
        "secure": true,
        "value": "9065918742607982171_rO417KADJBExerAv0SKG17ZgWP3FgquAkIpbYKDKu4X",
        "version": 0
      },
      {
        "comment": null,
        "comment_url": null,
        "discard": false,
        "domain": ".vk.ru",
        "domain_initial_dot": true,
        "domain_specified": true,
        "expires": null,
        "name": "remixsid",
        "path": "/",
        "path_specified": true,
        "port": null,
        "port_specified": false,
        "rest": {
          "HttpOnly": null
        },
        "rfc2109": false,
        "secure": true,
        "value": "1_D6VZUJAobUmz859PGu9Aql6SmBxRRWkWKY5U-WHquxx-EOazytQfLMCcxLTsYl8w1ETcsy0HqvQgQuoP-mE5lg",
        "version": 0
      },
      {
        "comment": null,
        "comment_url": null,
        "discard": false,
        "domain": ".vk.ru",
        "domain_initial_dot": true,
        "domain_specified": true,
        "expires": null,
        "name": "remixnttpid",
        "path": "/",
        "path_specified": true,
        "port": null,
        "port_specified": false,
        "rest": {
          "HttpOnly": null
        },
        "rfc2109": false,
        "secure": true,
        "value": "vk1.a.DNqYwQknWdnOpmVK89nU9_bkUSfMWIT1PGfSwRBzZINrWM20TQsb4kWnLefn8mHumv0UEyqZ5NgGpjkifRkVt90__nyBWxAcIT6antyPDabBsyP4TF5l1aBQBZUs2UxDqAhybEto3zcYxuF1xEWd999pMdOeEoaFHXHIGR2PCv1XDT487KYG3BHDTnA4aAM3",
        "version": 0
      },
      {
        "comment": null,
        "comment_url": null,
        "discard": false,
        "domain": ".vk.ru",
        "domain_initial_dot": true,
        "domain_specified": true,
        "expires": null,
        "name": "remixdmgr",
        "path": "/",
        "path_specified": true,
        "port": null,
        "port_specified": false,
        "rest": {
          "HttpOnly": null
        },
        "rfc2109": false,
        "secure": true,
        "value": "72455964c5177c9be9e6b8e94110856ca9a2af5da98f53eb5926e9ff2dbddd2e",
        "version": 0
      },
      {
        "comment": null,
        "comment_url": null,
        "discard": false,
        "domain": ".login.vk.ru",
        "domain_initial_dot": false,
        "domain_specified": true,
        "expires": null,
        "name": "p",
        "path": "/",
        "path_specified": true,
        "port": null,
        "port_specified": false,
        "rest": {
          "HttpOnly": null
        },
        "rfc2109": false,
        "secure": true,
        "value": "vk1.a.vY_l9i66vyTBBKzTvc2kHr9pxWVzazw6rkltVRZ-FAyD3vE9mGe_tHTkinowWp5_r-ISJU69uR5UYFY5kt2N4OSHJOgzVI6oQDtKiKAPkZyhziXbg51OiKjdlecTLpdbBhxXF6dW-3WV7r5N1xwgzdN_FS7pSereG6RISGmobAE",
        "version": 0
      }
    ],
    "token": {
      "app6287487": {
        "scope_140492255": {
          "access_token": "vk1.a.VeBnriDgijYp1nXB2DXf9RVVm2yBv_y9HNhg3KSJNO6WLKloeZHY4vlGzVABselBG7b9g8LO3OgZCktoV5HVXPlFaYCYe-PhM3hH-deIi3qwX976zTmf2d92_r0FIQnz3H53XCZCrrTvzTxZ5Kv0hzMHxc_UqhKeNNT3RhADEyRuTzgmChP4fdI_gTp5IfcgEifgalqeV2rqSKoK-na5bA",
          "expires_in": "86400",
          "user_id": "617202016"
        }
      }
    }
  }
}